ezform/__init__.py
ezform/apps.py
ezform/base.py
ezform/constant.py
ezform/db.py
ezform/encoding.py
ezform/exception.py
ezform/models.py
ezform/settings.py
ezform/utils.py
ezform/fields/__init__.py
ezform/fields/html.py
ezform/fields/internal.py
ezform/fields/rest.py
ezform/fields/validation.py
ezform/management/__init__.py
ezform/management/base.py
ezform/management/commands/__init__.py
ezform-2020.8.6.dist-info/METADATA
ezform-2020.8.6.dist-info/WHEEL
ezform-2020.8.6.dist-info/top_level.txt
ezform-2020.8.6.dist-info/RECORD
