Metadata-Version: 2.1
Name: ezform
Version: 2020.8.6
Summary: simple extensions to Django form
Author-email: Xingeng Chen <cxg@studio.home>
License: Apache License
Project-URL: Homepage, http://rcs.studio.home/project/ezform
Keywords: Django,Data Validation
Classifier: Development Status :: 5 - Production/Stable
Classifier: Intended Audience :: Developers
Classifier: License :: OSI Approved :: Apache Software License
Classifier: Operating System :: OS Independent
Classifier: Programming Language :: Python
Classifier: Programming Language :: Python :: 3
Classifier: Programming Language :: Python :: 3 :: Only
Classifier: Topic :: Software Development :: Libraries :: Python Modules
Requires-Python: >=3.8
Requires-Dist: Django >=4
Requires-Dist: dmprj
Requires-Dist: dsgen
Provides-Extra: calendar
Requires-Dist: numpy ; extra == 'calendar'
Requires-Dist: pandas ; extra == 'calendar'
Provides-Extra: redis
Requires-Dist: redis ; extra == 'redis'
Provides-Extra: rest
Requires-Dist: djangorestframework ; extra == 'rest'
Provides-Extra: s3
Requires-Dist: django-boto3 ; extra == 's3'
Requires-Dist: django-storage ; extra == 's3'
